pysmq/__init__.py
pysmq/_version.py
pysmq/client.py
pysmq/config.py
pysmq/exceptions.py
pysmq/proto/__init__.py
pysmq/proto/smq_pb2.py
pysmq/proto/smq_pb2_grpc.py
pysmq-1.0.7.dist-info/METADATA
pysmq-1.0.7.dist-info/WHEEL
pysmq-1.0.7.dist-info/top_level.txt
pysmq-1.0.7.dist-info/RECORD
